sqliteshelve/__init__.py
sqliteshelve/cli.py
sqlite_shelve-2.2.1.dist-info/LICENSE
sqlite_shelve-2.2.1.dist-info/METADATA
sqlite_shelve-2.2.1.dist-info/WHEEL
sqlite_shelve-2.2.1.dist-info/entry_points.txt
sqlite_shelve-2.2.1.dist-info/top_level.txt
sqlite_shelve-2.2.1.dist-info/RECORD
