Metadata-Version: 2.1
Name: sqlite-shelve
Version: 2.2.1
Summary: A SQLite implementation of the Python Shelf interface
Home-page: https://github.com/devnull255/sqlite-shelve
Author: Michael Mabin
Author-email: d3vvnull@gmail.com
Project-URL: Bug Tracker, https://github.com/devnull255/sqlite-shelve/issues
Classifier: Programming Language :: Python :: 3
Classifier: License :: OSI Approved :: MIT License
Classifier: Operating System :: OS Independent
Requires-Python: >=3.6
License-File: LICENSE
